webpi/__init__.py
webpi/app.py
webpi/users.py
webpi/wsgi.py
webpi-0.0.4.dist-info/METADATA
webpi-0.0.4.dist-info/WHEEL
webpi-0.0.4.dist-info/entry_points.txt
webpi-0.0.4.dist-info/top_level.txt
webpi-0.0.4.dist-info/RECORD
