Metadata-Version: 2.1
Name: webpi
Version: 0.0.4
Summary: Deep release notes helps you manage release notes for your project.
Home-page: https://github.com/urbas/webpi
Author: Matej Urbas
Author-email: matej.urbas@gmail.com
License: MIT license
Keywords: webpi
Platform: UNKNOWN
Classifier: Development Status :: 2 - Pre-Alpha
Classifier: Intended Audience :: Developers
Classifier: License :: OSI Approved :: MIT License
Classifier: Natural Language :: English
Classifier: Programming Language :: Python :: 3.6
Classifier: Programming Language :: Python :: 3.7
Requires-Dist: flask (>=1)
Requires-Dist: Flask-Login (>=0.4.1)
Requires-Dist: pyyaml (>=5.3)
